odoo/addons/ssi_voucher_cheque/README.rst
odoo/addons/ssi_voucher_cheque/__init__.py
odoo/addons/ssi_voucher_cheque/__manifest__.py
odoo/addons/ssi_voucher_cheque/menu.xml
odoo/addons/ssi_voucher_cheque/data/account_voucher_type_data.xml
odoo/addons/ssi_voucher_cheque/data/approval_template_cheque_payment_data.xml
odoo/addons/ssi_voucher_cheque/data/approval_template_cheque_receipt_data.xml
odoo/addons/ssi_voucher_cheque/data/ir_sequence_data.xml
odoo/addons/ssi_voucher_cheque/data/ir_windows_action_data.xml
odoo/addons/ssi_voucher_cheque/data/policy_template_cheque_payment_data.xml
odoo/addons/ssi_voucher_cheque/data/policy_template_cheque_receipt_data.xml
odoo/addons/ssi_voucher_cheque/data/sequence_template_cheque_payment_data.xml
odoo/addons/ssi_voucher_cheque/data/sequence_template_cheque_receipt_data.xml
odoo/addons/ssi_voucher_cheque/models/__init__.py
odoo/addons/ssi_voucher_cheque/models/cheque_payment.py
odoo/addons/ssi_voucher_cheque/models/cheque_receipt.py
odoo/addons/ssi_voucher_cheque/models/mixin_cheque_voucher.py
odoo/addons/ssi_voucher_cheque/security/ir.model.access.csv
odoo/addons/ssi_voucher_cheque/security/ir_module_category_data.xml
odoo/addons/ssi_voucher_cheque/security/ir_rule_data.xml
odoo/addons/ssi_voucher_cheque/security/res_group_data.xml
odoo/addons/ssi_voucher_cheque/static/description/banner.png
odoo/addons/ssi_voucher_cheque/static/description/icon.png
odoo/addons/ssi_voucher_cheque/views/account_cheque_payment_views.xml
odoo/addons/ssi_voucher_cheque/views/account_cheque_receipt_views.xml
odoo/addons/ssi_voucher_cheque/views/account_cheque_voucher_views.xml
odoo14_addon_ssi_voucher_cheque-14.0.2.3.0.dist-info/METADATA
odoo14_addon_ssi_voucher_cheque-14.0.2.3.0.dist-info/WHEEL
odoo14_addon_ssi_voucher_cheque-14.0.2.3.0.dist-info/top_level.txt
odoo14_addon_ssi_voucher_cheque-14.0.2.3.0.dist-info/RECORD
